{
  "author": "예문관(조선) 편",
  "bibliography_json": {
    "MF": "MF35-600",
    "간행년(서기력)": "*-*",
    "간행년(왕력)": "高宗年間寫",
    "간행처": "미상",
    "대표서명": "표제에 의함",
    "등록번호": "41020074v1",
    "서명": "頒敎文謄錄n1-1책",
    "소장처": "한국학중앙연구원",
    "언어": "한문",
    "인기": "印:藏書閣印",
    "종이재질": "紙質 : 楮紙",
    "주제분류": "史部, 政史類, 其他",
    "청구기호": "k2-3646",
    "판사항": "原本",
    "편저자한글(한자)": "예문관(조선) 편(藝文館(朝鮮) 編)",
    "표지제한글(한자)": "반교문등록(頒敎文謄錄)",
    "한글서명": "반교문등록",
    "형태서지": "\"線裝 1冊(40張): 左右雙邊, 半郭 25.6 × 24 cm, 烏絲欄, 半葉 15行字數不定, 註雙行, 內向二葉花紋魚尾; 32 × 29.3 cm\""
  },
  "book_id": "kh2_je_a_vsu_23646_000",
  "haje": {},
  "haje_text": "",
  "has_haje": false,
  "source_url": "http://yoksa.aks.ac.kr/jsp/aa/InfoView.jsp?aa10no=kh2_je_a_vsu_23646_000",
  "title_hanja": "頒敎文謄錄n1-1책",
  "title_ko": "반교문등록",
  "year": "高宗年間寫"
}
