{
  "author": "편자미상",
  "bibliography_json": {
    "MF": "MF35-747",
    "간행년(서기력)": "1936-미상",
    "간행처": "미상",
    "대표서명": "표제에 의함",
    "등록번호": "41006822v1",
    "서명": "東津日記",
    "소장처": "한국학중앙연구원",
    "언어": "한문",
    "인기": "李王家圖書之章",
    "청구기호": "K2-202",
    "판사항": "筆寫本",
    "편저자한글(한자)": "편자미상(編者未詳)",
    "표지제한글(한자)": "동진일기(東津日記)",
    "한글서명": "동진일기",
    "형태서지": "線裝 1冊(34張) ; 27 × 19.7cm"
  },
  "book_id": "kh2_je_a_vsu_20202_000",
  "haje": {},
  "haje_text": "",
  "has_haje": false,
  "source_url": "http://yoksa.aks.ac.kr/jsp/aa/InfoView.jsp?aa10no=kh2_je_a_vsu_20202_000",
  "title_hanja": "東津日記",
  "title_ko": "동진일기",
  "year": "1936-미상"
}
