{
  "article_id": "22592_001_0035",
  "body_hanja": "王世子嬪三揀擇時大臣ㆍ禮官\n命招詣\n闕領議政申欽ㆍ右議政金瑬ㆍ海昌君尹昉ㆍ禮曹判書金尙容ㆍ參判韓汝溭進",
  "book_id": "kh2_je_a_vsu_22592_000",
  "book_title_hanja": "嘉禮都監儀軌",
  "book_title_ko": "가례도감의궤",
  "entities": [],
  "meaning_ko": "",
  "reading_ko": "",
  "source_url": "http://yoksa.aks.ac.kr/jsp/aa/VolView.jsp?aa10no=kh2_je_a_vsu_22592_001&aa15no=001&aa20no=22592_001_0035",
  "title_hanja": "九月二十九日",
  "title_ko": "구월이십구일",
  "translation_ko": "",
  "translation_status": "missing",
  "volume_id": "kh2_je_a_vsu_22592_001"
}