{
  "article_id": "22589_001_0004",
  "body_hanja": "啓曰時任臺諫·都監·郞廳\n啓下終始察任之例著戊寅年嘉禮都監謄錄而丙申年則時任臺諫·郞廳\n啓下之後旋卽改差或改或否前後殊例故臣曹不敢以臆見斷其可否嘉禮都監郞廳李翊相改差與否援據前後規例以\n稟矣伏聞頃日\n引見時自\n上下殊涉矇矓之\n敎大臣亦以時任臺諫·郞廳差下不當之意有所陳\n達不勝惶恐依丙申年前例嘉禮都監郞廳李翊相改差何如\n傳曰允\n都監事目\n今此嘉禮時應行諸事一依前例磨鍊後錄爲白去乎依此施行何如\n一郞廳八員內司直李端夏·弘文館應敎洪柱三都廳稱號其餘六員分三房爲白齊\n一堂上·郞廳·監造官除本司仕上直凡公會勿參差\n祭安徐除服制式暇臺諫外任勿差爲白齊\n一堂上·都廳印信各一顆行用爲白齊\n一監造官六員差出分三房爲白齊\n一員役錄事一·書寫一·書員三·庫直四·使令二十名乙良令戶·兵曹給料布爲白乎矣書吏十二人則各司受料人以兼爲使喚爲白齊\n一應役匠人厭避者·各司下人違令者直囚笞罰爲白齊\n一各司官員緩慢尤甚者啓\n聞推治爲白齊\n一各色匠人閭閻間絶無尙衣院·觀象監匠人及上司衙門皁隸·羅將掖庭署下人諸宮家私匠人都監砲殺手中可合供役者依例使喚爲白齊\n一行用紙地筆墨及各色雜物令各該司進排爲白乎矣鋪陳諸具段依近例各自本衙門取來行用以除殘司一分之弊爲白齊\n一諸色匠人償役價布令左兵曹量數上下爲白齊\n一別工作排設監役官令繕工監勤斡官員差定爲白乎矣書員一·庫直一·使令一·令戶·兵曹給價役軍乙良兵曹量數定送爲白齊\n一別宮修理所書員·庫直·使令各一限事畢間亦令戶·兵曹給料布爲白齊\n一始役日爲始監造官輪回直宿爲白齊\n一各房守直軍士令兵曹照例定送爲白齊\n一處所乙良刑曹·工曹通用排設爲白齊\n一堂上·郞廳各房茶母乙良置依近例各自本衙門定送爲白齊\n一未盡條件追乎磨諫啓\n聞施行爲白齊",
  "book_id": "kh2_je_a_vsu_22589_000",
  "book_title_hanja": "嘉禮都監",
  "book_title_ko": "가례도감",
  "entities": [],
  "meaning_ko": "",
  "reading_ko": "",
  "source_url": "http://yoksa.aks.ac.kr/jsp/aa/VolView.jsp?aa10no=kh2_je_a_vsu_22589_001&aa15no=001&aa20no=22589_001_0004",
  "title_hanja": "庚戌九月十八日 吏曹",
  "title_ko": "경술구월십팔일 이조",
  "translation_ko": "",
  "translation_status": "missing",
  "volume_id": "kh2_je_a_vsu_22589_001"
}