{
  "article_id": "22589_001_0073",
  "body_hanja": "一都廳所用大樻子一部具鎖鑰·房舍所用鎖鑰二部·庫間所用鎖鑰一部等用還次以進排事[주:戶曹·繕工監]\n一都提調坐起時大廳所用大地衣一部·行步席一番及歇所廳所用小地衣一部·大屛風一坐·紅紬案席一坐·登每一坐等用還次以進排事[주:戶曹·濟用監·長興庫·]\n一都廳所用瓦燈二部·鍮唾口二部·大硯滴一部·雨傘二柄·延▼원문보기48b처음으로日礪石一塊·房舍所用小地衣一浮·登每二坐及堂上坐·起時所用六張付地衣一浮用還次以進排事[주:戶曹·繕工監·平市·長興庫·軍器寺·工曹]",
  "book_id": "kh2_je_a_vsu_22589_000",
  "book_title_hanja": "嘉禮都監",
  "book_title_ko": "가례도감",
  "entities": [],
  "meaning_ko": "",
  "reading_ko": "",
  "source_url": "http://yoksa.aks.ac.kr/jsp/aa/VolView.jsp?aa10no=kh2_je_a_vsu_22589_001&aa15no=001&aa20no=22589_001_0073",
  "title_hanja": "庚戌九月二十三日",
  "title_ko": "경술구월이십삼일",
  "translation_ko": "",
  "translation_status": "missing",
  "volume_id": "kh2_je_a_vsu_22589_001"
}