{
  "article_id": "22589_001_0108",
  "body_hanja": "一本房所掌各樣擔陪負持軍及領去部將·各差備忠贊衛等磨鍊後錄爲去乎依前例今月十四日六禮習儀前期定送都監良中逢點事兵曹良中捧甘何如堂上手決依\n腰轝四部擔陪軍各十名領去部將八人差備忠贊衛八人\n馬木軍八名雨備軍四名\n排案床一部負持軍二名差備軍忠贊衛二人\n雨備軍一名[주:以上兵曹]\n支擧十部負持軍十名[주:司僕寺]\n函床七部負持軍各二名鋪陳軍十名\n雜物負持軍十名",
  "book_id": "kh2_je_a_vsu_22589_000",
  "book_title_hanja": "嘉禮都監",
  "book_title_ko": "가례도감",
  "entities": [],
  "meaning_ko": "",
  "reading_ko": "",
  "source_url": "http://yoksa.aks.ac.kr/jsp/aa/VolView.jsp?aa10no=kh2_je_a_vsu_22589_001&aa15no=001&aa20no=22589_001_0108",
  "title_hanja": "辛亥二月十二日",
  "title_ko": "신해이월십이일",
  "translation_ko": "",
  "translation_status": "missing",
  "volume_id": "kh2_je_a_vsu_22589_001"
}