{
  "article_id": "22595_002_0051",
  "body_hanja": "今此嘉禮敎是時妃受冊親迎外習儀及冊妃親迎同牢宴內外習儀等所用雜物各其司官員躬親進排爲旀正日段置一體待令事捧甘何如[주:手決內依]後妃受冊習儀敎是時所用假玉冊一件假金寶一件[주:以上別工作]差備‧忠贊衛各二員[주:兵曹]假褥席各一件[주:長興庫濟用監]紅紬巾各一件[주:濟用監]寶鞍一部[주:工曹]寶載馬一匹[주:內司僕寺]牽馬陪所着黃草笠二部[주:戶曹]乻只紅木二十尺[주:濟用監]假函二部[주:工曹]紅紬袱各一件[주:濟用監]差備忠贊衛各一員[주:兵曹]排案床各一坐[주:繕工監]紅紬巾各一件[주:濟用監]差備忠贊衛各二員[주:兵曹]紅毛氈一浮[주:戶曹]鞍籠一部[주:長興庫]靑衣帶各二件[주:濟用監]冊妃親迎及同牢宴內外習儀敎是時所用假玉冊一件假金寶一件[주:以上別工作]紅紬袱各一件[주:濟用監]排案床各一坐[주:尙衣院]紅紬巾各一件[주:濟用監]假函各一件[주:尙衣院]紅紬巾各一件[주:濟用監]讀寶床一坐讀冊床一坐[주:以上別工作]紅紬袱各一件[주:濟用監]假褥席各一件[주:長興庫‧濟用監]親迎敎是時所用燭臺一雙[주:工曹]同牢宴習儀敎是時所用饌案床二坐高足床六坐小盤及各樣器皿[주:隨所入]香案床二坐樽臺二部酒亭一坐□□兒二雙銀盞二雙臺具紅眞絲細繩三十尺銀甁一坐沙樽二坐各樣床巾袱屬[주:以上尙衣院濟用監‧司饔院]燭臺二雙香爐二坐香盒二坐[주:以上工曹]座面紙八張[주:長興庫]卓衣八件[주:濟用監]卓衣朴只廣頭釘[주:別工作]",
  "book_id": "kh2_je_a_vsu_22595_000",
  "book_title_hanja": "嘉禮都監儀軌n1-2책",
  "book_title_ko": "가례도감의궤",
  "entities": [],
  "meaning_ko": "",
  "reading_ko": "",
  "source_url": "http://yoksa.aks.ac.kr/jsp/aa/VolView.jsp?aa10no=kh2_je_a_vsu_22595_002&aa15no=002&aa20no=22595_002_0051",
  "title_hanja": "壬戌九月初七日",
  "title_ko": "임술구월초칠일",
  "translation_ko": "",
  "translation_status": "missing",
  "volume_id": "kh2_je_a_vsu_22595_002"
}