{
  "article_id": "D4B^49_001_0369",
  "body_hanja": "擧網得魚니狀如松江之鱸라顓童齎呈니只恨無酒오이다弟某拜\n○答\n瓮香이方濃에徒歎無肴러니叨惠佳肴니亦歎無客이리[교정주:라]希卽光臨이如何오\n弟某拜",
  "book_id": "kh2_je_a_vsu_D4B^49_000",
  "book_title_hanja": "(新編) 尺牘大方",
  "book_title_ko": "(신편) 척독대방",
  "entities": [],
  "meaning_ko": "",
  "reading_ko": "",
  "source_url": "http://yoksa.aks.ac.kr/jsp/aa/VolView.jsp?aa10no=kh2_je_a_vsu_D4B%5E49_001&aa15no=001&aa20no=D4B%5E49_001_0369",
  "title_hanja": "十、饋魚",
  "title_ko": "십、궤어",
  "translation_ko": "",
  "translation_status": "missing",
  "volume_id": "kh2_je_a_vsu_D4B^49_001"
}