{
  "article_id": "D4B^49_001_0258",
  "body_hanja": "그림속텍스트:長三月그림속텍스트:從祖祖父그림속텍스트:中從下無服그림속텍스트:長三月그림속텍스트:從祖祖姑그림속텍스트:中從下無服그림속텍스트:長三月그림속텍스트:從祖父그림속텍스트:中從下無服그림속텍스트:長九月그림속텍스트:伯叔父그림속텍스트:中七月그림속텍스트:下五月그림속텍스트:姑그림속텍스트:長九月그림속텍스트:中七月그림속텍스트:下五月그림속텍스트:長三月그림속텍스트:從祖姑그림속텍스트:中從下無服그림속텍스트:長三月그림속텍스트:從祖兄弟그림속텍스트:中從下無服그림속텍스트:長五月그림속텍스트:從父兄弟그림속텍스트:中從上그림속텍스트:下三月그림속텍스트:兄弟그림속텍스트:長九月그림속텍스트:中七月그림속텍스트:下五月그림속텍스트:己그림속텍스트:姊妹그림속텍스트:長九月그림속텍스트:中七月그림속텍스트:下五月그림속텍스트:長九月그림속텍스트:從父姊妹그림속텍스트:中從上下三月그림속텍스트:長三月그림속텍스트:從祖姊妹그림속텍스트:中從下無服그림속텍스트:長三月그림속텍스트:從父兄弟之子그림속텍스트:中從下無服그림속텍스트:長九月그림속텍스트:兄弟之子그림속텍스트:中七月그림속텍스트:下五月그림속텍스트:子그림속텍스트:長九月그림속텍스트:中七月그림속텍스트:下五月그림속텍스트:長九月그림속텍스트:兄弟之女그림속텍스트:中七月그림속텍스트:下五月그림속텍스트:長三月그림속텍스트:從父兄弟之女그림속텍스트:中從下無服그림속텍스트:大功之殤中從上그림속텍스트:齊衰之殤亦中從上그림속텍스트:小功之殤中從下그림속텍스트:此丈夫爲殤者服也그림속텍스트:長三月그림속텍스트:兄弟之孫그림속텍스트:中從下無服그림속텍스트:孫그림속텍스트:嫡그림속텍스트:長九月그림속텍스트:中七月그림속텍스트:下五月그림속텍스트:衆그림속텍스트:長五月그림속텍스트:中從上그림속텍스트:下三月그림속텍스트:長三月그림속텍스트:兄弟之孫女그림속텍스트:中從下無服그림속텍스트:長三月그림속텍스트:嫡曾玄孫그림속텍스트:中七月그림속텍스트:下五月그림속텍스트:齊衰之殤中從上그림속텍스트:大功之殤中從下그림속텍스트:小功之殤亦中從下그림속텍스트:此妻爲夫黨殤者服也",
  "book_id": "kh2_je_a_vsu_D4B^49_000",
  "book_title_hanja": "(新編) 尺牘大方",
  "book_title_ko": "(신편) 척독대방",
  "entities": [],
  "meaning_ko": "",
  "reading_ko": "",
  "source_url": "http://yoksa.aks.ac.kr/jsp/aa/VolView.jsp?aa10no=kh2_je_a_vsu_D4B%5E49_001&aa15no=001&aa20no=D4B%5E49_001_0258",
  "title_hanja": "三殤降服之圖",
  "title_ko": "삼상강복지도",
  "translation_ko": "",
  "translation_status": "missing",
  "volume_id": "kh2_je_a_vsu_D4B^49_001"
}