{
  "article_id": "D4B^49_001_0080",
  "body_hanja": "拜頌\n調安",
  "book_id": "kh2_je_a_vsu_D4B^49_000",
  "book_title_hanja": "(新編) 尺牘大方",
  "book_title_ko": "(신편) 척독대방",
  "entities": [],
  "meaning_ko": "조선 후기 공문서에서 사용된 간결한 인사 말투이다. 상대의 안녕과 건강을 기원하는 우의(友誼) 표현으로, '拜頌'은 상대방을 존경하고 찬사를 표한다는 의미의 경어체 인사로, '調安'은 몸과 마음을 조리며 안녕하게 지내라는 뜻의 축원어구이다. 본문 내용이 두 구절뿐이라 구체적 맥락 파악이 어렵지만, 개인 서신이나 외교 문서의 서두·끝자락에서 볼 수 있는 격식 높은 인사 표현으로 추정된다.",
  "reading_ko": "배송 조안",
  "source_url": "http://yoksa.aks.ac.kr/jsp/aa/VolView.jsp?aa10no=kh2_je_a_vsu_D4B%5E49_001&aa15no=001&aa20no=D4B%5E49_001_0080",
  "title_hanja": "二十、疾病",
  "title_ko": "이십、질병",
  "translation_ko": "올려 경의를 표하며, 늘 안녕하시기를 기원합니다.",
  "translation_status": "ok",
  "volume_id": "kh2_je_a_vsu_D4B^49_001"
}