{
  "article_id": "D4B^49_001_0357",
  "body_hanja": "敝友某君이詩文이佳麗고器宇磊落야眞風流儒雅也[주:杜詩云、風流儒雅亦吾師]라夙慕龍門[주:士有容接李膺者、名爲登龍門]야弟爲介紹니倘容僦居[주:賃居]야常通問聞이면俾其久事荊州[주:李白、與韓荊州書云、願識韓荊州]로以慰生平素願이오否則夢境이迷離에終歸山斗[주:韓愈文望如泰山北斗]耳라其奈之何오臨書에不勝眷注노이다弟某拜\n○答\n某君이馳騁晉唐고抗衡李杜[주:李白杜甫]야聲名이遠播니卽不爲彼揄揚[주:卽頌揚]이라而到處에自多優待者러니叨兄薦牘[주:謂以書擧薦]니俾得延爲上客야叩求蘭誨[주:謂芝蘭之言]리니倘不惜齒牙[주:謂誦言]耶아呵呵오이다弟某拜",
  "book_id": "kh2_je_a_vsu_D4B^49_000",
  "book_title_hanja": "(新編) 尺牘大方",
  "book_title_ko": "(신편) 척독대방",
  "entities": [],
  "meaning_ko": "",
  "reading_ko": "",
  "source_url": "http://yoksa.aks.ac.kr/jsp/aa/VolView.jsp?aa10no=kh2_je_a_vsu_D4B%5E49_001&aa15no=001&aa20no=D4B%5E49_001_0357",
  "title_hanja": "九、薦門人",
  "title_ko": "구、천문인",
  "translation_ko": "",
  "translation_status": "missing",
  "volume_id": "kh2_je_a_vsu_D4B^49_001"
}