{
  "article_id": "D4B^49_001_0317",
  "body_hanja": "枕底에聞梧桐滴滴[주:唐詩云、枕底梧桐滴滴雨]니夬好炎帝火輪이歸屬過境이라伏惟新凉에兄體旅旺가景溯頂祝이라弟約與數三人으로辦出如干股金야買一屋子於廣橋川邊고近設雜貨鋪니吾兄은同是意中이라簿記委任을已經本鋪收議고謹此仰述니兄其肯許否아勿靳을是荷라耑此不戩노이다弟某拜\n○答\n洛陽城裏에秋風이忽起니江東歸思[주:張翰詩云、秋風忽憶江東行]가日益深切이라方擬日間理裝터니忽承意外寵眷야叨荷貴鋪簿記之任니可感其盛意나奈文算이未嫺야不堪其任에何오徒增悚歉이라餘容拜陳이오先此肅復노이다\n弟某拜",
  "book_id": "kh2_je_a_vsu_D4B^49_000",
  "book_title_hanja": "(新編) 尺牘大方",
  "book_title_ko": "(신편) 척독대방",
  "entities": [],
  "meaning_ko": "",
  "reading_ko": "",
  "source_url": "http://yoksa.aks.ac.kr/jsp/aa/VolView.jsp?aa10no=kh2_je_a_vsu_D4B%5E49_001&aa15no=001&aa20no=D4B%5E49_001_0317",
  "title_hanja": "五、雜貨商",
  "title_ko": "오、잡화상",
  "translation_ko": "",
  "translation_status": "missing",
  "volume_id": "kh2_je_a_vsu_D4B^49_001"
}