{
  "author": "예조(조선) 편",
  "bibliography_json": {
    "MF": "MF35-628",
    "간행년(서기력)": "1630-*",
    "간행년(왕력)": "仁祖 8(1630) 寫",
    "간행처": "미상",
    "대표서명": "권수제(권두서명)에 의함",
    "등록번호": "41017286v1",
    "서명": "穆陵遷葬時謄錄n1-1책",
    "소장처": "한국학중앙연구원",
    "언어": "한문",
    "인기": "印:禮曹 之印 藏書閣印",
    "종이재질": "紙質 : 楮紙",
    "주제분류": "史部, 政書類, 典禮, 陵/園/墓",
    "청구기호": "k2-2311",
    "판사항": "原本",
    "편저자한글(한자)": "예조(조선) 편(禮曹(朝鮮) 編)",
    "한글서명": "목릉천장시등록",
    "형태서지": "\"線裝, 1冊(12張): 四周單邊, 半郭 31.8 × 21cm, 烏絲欄, 半葉 10行 18字, 內向二葉花紋魚尾; 39.8 × 19.7cm\""
  },
  "book_id": "kh2_je_a_vsu_22311_000",
  "haje": {},
  "haje_text": "",
  "has_haje": false,
  "source_url": "http://yoksa.aks.ac.kr/jsp/aa/InfoView.jsp?aa10no=kh2_je_a_vsu_22311_000",
  "title_hanja": "穆陵遷葬時謄錄n1-1책",
  "title_ko": "목릉천장시등록",
  "year": "仁祖 8(1630) 寫"
}
